[{"id":1460947855744,"TwitterUser":"eee","TextInput":""},{"id":1460946831478,"TwitterUser":"whee","TextInput":""},{"id":1460946785192,"TwitterUser":"ha","TextInput":""},{"id":1460946766426,"TwitterUser":"d","TextInput":""},{"id":1460946689565,"TwitterUser":"mii","TextInput":"mii"},{"id":1460946445559,"TwitterUser":"new","TextInput":"test"},{"id":1460593780065,"TwitterUser":"@apple","TextInput":"juice"},{"id":1460061744310,"TwitterUser":"@yumeng03","TextInput":""},{"id":1460059112822,"TwitterUser":"@yumeng","TextInput":""},{"id":1460043663335,"TwitterUser":"lala","TextInput":""},{"id":1460042379347,"TwitterUser":"lala","TextInput":""},{"id":1460042045793,"TwitterUser":"","TextInput":"hello"},{"id":1460042033805,"TwitterUser":"play","TextInput":""},{"id":1460041993259,"TwitterUser":"hey","TextInput":""},{"id":1460007107510,"TwitterUser":"yumeng","TextInput":""},{"id":1460007076104,"TwitterUser":"yumeng","TextInput":""},{"id":1460007034229,"TwitterUser":"da","TextInput":""},{"id":1460006970426,"TwitterUser":"","TextInput":"lala"},{"id":1460006938616,"TwitterUser":"adfef","TextInput":""},{"id":1460006905721,"TwitterUser":"daf","TextInput":""},{"id":1460006889519,"TwitterUser":"dfae","TextInput":""},{"id":1460006849551,"TwitterUser":"dfae","TextInput":""},{"id":1460006819660,"TwitterUser":"dafe","TextInput":""},{"id":1460006818268,"TwitterUser":"dafe","TextInput":""},{"id":1460006754829,"TwitterUser":"apple","TextInput":""},{"id":1460006702520,"TwitterUser":"yumeng","TextInput":""},{"id":1460006690025,"TwitterUser":"yumeng","TextInput":""},{"id":1460006649472,"TwitterUser":"dfd","TextInput":""},{"id":1460006526207,"TwitterUser":"dfd","TextInput":""},{"id":1460006512280,"TwitterUser":"fafaf","TextInput":""},{"id":1460006330754,"TwitterUser":"","TextInput":"daf"},{"id":1460006327094,"TwitterUser":"adafd","TextInput":""},{"id":1460006293493,"TwitterUser":"a","TextInput":""},{"id":1460004706571,"TwitterUser":"efefefefef","TextInput":""},{"id":1459630992012,"TwitterUser":"hi","TextInput":"test"},{"id":1459486523632,"TwitterUser":"@lalala","TextInput":"hello"},{"id":1459486437048,"TwitterUser":"@yumeng03","TextInput":"sleep"},{"id":1459486351271,"TwitterUser":"lalala","TextInput":"hehe"}]